{
    "Su\u0146i, kuc\u0113ni": "/lv/animals/dogs/",
    "Ka\u0137i, ka\u0137\u0113ni": "/lv/animals/cats/",
    "Grauz\u0113ji": "/lv/animals/rodents/",
    "Papagai\u013ci un putni": "/lv/animals/parrots-and-birds/",
    "Zivti\u0146as, akv\u0101riji": "/lv/animals/fish/",
    "Eksotiskie dz\u012bvnieki": "/lv/animals/exotic-animals/",
    "Lauksaimniec\u012bbas dz\u012bvnieki": "/lv/agriculture/animal-husbandry/agricultural-animals/",
    "Veterin\u0101rija": "/lv/animals/veterinary-medicine/",
    "Atrasts - pazaud\u0113ts": "/lv/home-stuff/searches-finds/",
    "Da\u017e\u0101di": "/lv/animals/other/"
}